auc/__init__.py
auc/network.py
auc-0.1.0.dist-info/METADATA
auc-0.1.0.dist-info/WHEEL
auc-0.1.0.dist-info/licenses/LICENSE
auc-0.1.0.dist-info/RECORD
