Metadata-Version: 2.3
Name: auc
Version: 0.1.0
Summary: AUC network
Project-URL: Homepage, https://github.com/wensheng/auc
Project-URL: Bug Tracker, https://github.com/wensheng/auc/issues
Author-email: Wensheng Wang <wenshengwang@gmail.com>
License: Copyright (c) 2024 Wensheng Wang
Classifier: License :: OSI Approved :: MIT License
Classifier: Operating System :: OS Independent
Classifier: Programming Language :: Python :: 3
Requires-Python: >=3.8
